airprompt/__init__.py
airprompt/_base_client.py
airprompt/_client.py
airprompt/_compat.py
airprompt/_constants.py
airprompt/_exceptions.py
airprompt/_files.py
airprompt/_models.py
airprompt/_qs.py
airprompt/_resource.py
airprompt/_response.py
airprompt/_streaming.py
airprompt/_types.py
airprompt/_version.py
airprompt/py.typed
airprompt/_utils/__init__.py
airprompt/_utils/_logs.py
airprompt/_utils/_proxy.py
airprompt/_utils/_reflection.py
airprompt/_utils/_streams.py
airprompt/_utils/_sync.py
airprompt/_utils/_transform.py
airprompt/_utils/_typing.py
airprompt/_utils/_utils.py
airprompt/lib/.keep
airprompt/lib/langchain.py
airprompt/resources/__init__.py
airprompt/resources/prompts.py
airprompt/types/__init__.py
airprompt/types/prompt.py
airprompt/types/prompt_get_params.py
airprompt-0.1.0a7.dist-info/METADATA
airprompt-0.1.0a7.dist-info/WHEEL
airprompt-0.1.0a7.dist-info/licenses/LICENSE
airprompt-0.1.0a7.dist-info/RECORD
